LICENSE.txt
MANIFEST.in
README.md
requirements.txt
setup.py
decanter/__init__.py
decanter/_version.py
decanter/decanter-admin.py
decanter/decanter.py
decanter.egg-info/PKG-INFO
decanter.egg-info/SOURCES.txt
decanter.egg-info/dependency_links.txt
decanter.egg-info/requires.txt
decanter.egg-info/top_level.txt
decanter/app/__init__.py
decanter/app/bundles/__init__.py
decanter/app/bundles/home/__init__.py
decanter/app/bundles/home/controllers/__init__.py
decanter/app/bundles/home/controllers/index.py
decanter/app/common/__init__.py
decanter/app/common/errors.py
decanter/app/config/__init__.py
decanter/app/config/settings.py
decanter/app/plugin/__init__.py
decanter/app/plugins/__init__.py
decanter/lib/__init__.py
decanter/lib/config.py
decanter/lib/crypt.py
decanter/lib/decorator.py
decanter/lib/errors.py
decanter/lib/i18n.py
decanter/lib/jsonvalidation.py
decanter/lib/loaders.py
decanter/lib/logger.py
decanter/lib/middleware.py
decanter/lib/plugin.py
decanter/lib/session.py
decanter/lib/singleton.py
decanter/lib/store.py
decanter/vendor/__init__.py
decanter/vendor/daemon.py