Metadata-Version: 1.1
Name: decanter
Version: 0.1.9.0
Summary: A humble web framework based on bottle
Home-page: https://github.com/gengo/decanter
Author: Gengo
Author-email: UNKNOWN
License: BSD
Keywords: web framework bottle gengo
Platform: UNKNOWN
Classifier: Development Status :: 5 - Production/Stable
Classifier: Intended Audience :: Developers
Classifier: License :: OSI Approved :: BSD License
Classifier: Topic :: Software Development :: Libraries :: Python Modules
Classifier: Topic :: Internet
